odoo10_addon_product_uom-10.0.1.0.0-py2.7-nspkg.pth
odoo10_addon_product_uom-10.0.1.0.0.dist-info/top_level.txt
odoo10_addon_product_uom-10.0.1.0.0.dist-info/WHEEL
odoo10_addon_product_uom-10.0.1.0.0.dist-info/RECORD
odoo10_addon_product_uom-10.0.1.0.0.dist-info/metadata.json
odoo10_addon_product_uom-10.0.1.0.0.dist-info/DESCRIPTION.rst
odoo10_addon_product_uom-10.0.1.0.0.dist-info/METADATA
odoo10_addon_product_uom-10.0.1.0.0.dist-info/namespace_packages.txt
odoo/addons/product_uom/__manifest__.py
odoo/addons/product_uom/__init__.py
odoo/addons/product_uom/README.rst
odoo/addons/product_uom/data/product_uom_categ.xml
odoo/addons/product_uom/data/product_uom.xml
odoo/addons/product_uom/static/description/icon.png
