Metadata-Version: 2.0
Name: odoo10-addon-product-uom
Version: 10.0.1.0.0
Summary: Provide missing uom
Home-page: http://ursainfosystems.com
Author: Ursa Information Systems, Laslabs, Odoo Community Association (OCA)
Author-email: support@odoo-community.org
License: AGPL-3
Platform: UNKNOWN
Requires-Dist: odoo (<10.1dev,>=10.0)
Classifier: Programming Language :: Python :: 2.7
Classifier: Framework :: Odoo
Classifier: License :: OSI Approved :: GNU Affero General Public License v3
